odoo/addons/partner_accreditation/README.rst
odoo/addons/partner_accreditation/__init__.py
odoo/addons/partner_accreditation/__manifest__.py
odoo/addons/partner_accreditation/i18n/fr.po
odoo/addons/partner_accreditation/i18n/hr.po
odoo/addons/partner_accreditation/i18n/it.po
odoo/addons/partner_accreditation/i18n/partner_accreditation.pot
odoo/addons/partner_accreditation/models/__init__.py
odoo/addons/partner_accreditation/models/res_partner.py
odoo/addons/partner_accreditation/models/res_partner_accreditation.py
odoo/addons/partner_accreditation/readme/CONTRIBUTORS.rst
odoo/addons/partner_accreditation/readme/DESCRIPTION.rst
odoo/addons/partner_accreditation/security/ir.model.access.csv
odoo/addons/partner_accreditation/static/description/icon.png
odoo/addons/partner_accreditation/static/description/index.html
odoo/addons/partner_accreditation/views/res_partner_accreditation_view.xml
odoo/addons/partner_accreditation/views/res_partner_view.xml
odoo_addon_partner_accreditation-16.0.1.0.0.12.dist-info/METADATA
odoo_addon_partner_accreditation-16.0.1.0.0.12.dist-info/WHEEL
odoo_addon_partner_accreditation-16.0.1.0.0.12.dist-info/top_level.txt
odoo_addon_partner_accreditation-16.0.1.0.0.12.dist-info/RECORD
